plain/auth/CHANGELOG.md
plain/auth/README.md
plain/auth/__init__.py
plain/auth/default_settings.py
plain/auth/requests.py
plain/auth/sessions.py
plain/auth/templates.py
plain/auth/test.py
plain/auth/utils.py
plain/auth/views.py
plain_auth-0.21.0.dist-info/METADATA
plain_auth-0.21.0.dist-info/WHEEL
plain_auth-0.21.0.dist-info/licenses/LICENSE
plain_auth-0.21.0.dist-info/RECORD
