Metadata-Version: 2.4
Name: plain.auth
Version: 0.21.0
Summary: Add users to your app and decide what they can access.
Author-email: Dave Gaeddert <dave.gaeddert@dropseed.dev>
License-Expression: BSD-3-Clause
License-File: LICENSE
Requires-Python: >=3.13
Requires-Dist: plain-models<1.0.0
Requires-Dist: plain-sessions<1.0.0
Requires-Dist: plain<1.0.0
